src/__init__.py
src/main.py
src/pasTozihat.py
src/setup.py
mmda2-0.1.dist-info/METADATA
mmda2-0.1.dist-info/WHEEL
mmda2-0.1.dist-info/top_level.txt
mmda2-0.1.dist-info/RECORD
