Metadata-Version: 2.1
Name: mmda2
Version: 0.1
Summary: student managmnet
Home-page: 
Author: mmda2
Author-email: mohammadafshar0083@gmail.com
License: MIT
Keywords: managments
